portal/__init__.py
portal/connections/pipe_client.py
portal/connections/pipe_server.py
portal_ipc-0.0.1.dist-info/METADATA
portal_ipc-0.0.1.dist-info/WHEEL
portal_ipc-0.0.1.dist-info/top_level.txt
portal_ipc-0.0.1.dist-info/RECORD
